CHANGES.txt
MANIFEST.in
README.md
setup.py
GeobricksMetadataManager.egg-info/PKG-INFO
GeobricksMetadataManager.egg-info/SOURCES.txt
GeobricksMetadataManager.egg-info/dependency_links.txt
GeobricksMetadataManager.egg-info/requires.txt
GeobricksMetadataManager.egg-info/top_level.txt
examples/__init__.py
geobricks_metadata_manager/__init__.py
geobricks_metadata_manager/__init__.pyc
geobricks_metadata_manager/config/__init__.py
geobricks_metadata_manager/config/__init__.pyc
geobricks_metadata_manager/config/config.py
geobricks_metadata_manager/config/config.pyc
geobricks_metadata_manager/core/__init__.py
geobricks_metadata_manager/core/__init__.pyc
geobricks_metadata_manager/core/metadata_manager_d3s_core.py
geobricks_metadata_manager/core/metadata_manager_d3s_core.pyc
geobricks_metadata_manager/rest/__init__.py
geobricks_metadata_manager/rest/__init__.pyc
geobricks_metadata_manager/rest/metadata_manager_main.py
geobricks_metadata_manager/rest/metadata_manager_rest.py
geobricks_metadata_manager/rest/metadata_manager_rest.pyc
geobricks_metadata_manager/utils/__init__.pyc
geobricks_metadata_manager/utils/log.pyc
test/__init__.py
test/metadata_manager_test.py