Metadata-Version: 1.0
Name: GeobricksMetadataManager
Version: 0.1.1
Summary: Geobricks library to manage Metadata.
Home-page: http://pypi.python.org/pypi/GeobricksGeoserverManager/
Author: Simone Murzilli; Guido Barbaglia
Author-email: geobrickspy@gmail.com
License: LICENSE.txt
Keywords: geobricks,metadata,d3s
Platform: UNKNOWN
